my_cont/__init__.py
my_cont/__main__.py
my_cont-1.1.5.dist-info/METADATA
my_cont-1.1.5.dist-info/WHEEL
my_cont-1.1.5.dist-info/entry_points.txt
my_cont-1.1.5.dist-info/RECORD
