Metadata-Version: 2.3
Name: my-cont
Version: 1.1.5
Summary: 
Author: Pavel Kirilin
Author-email: win10@list.ru
Requires-Python: >=3.11,<4.0
Classifier: Programming Language :: Python :: 3
Classifier: Programming Language :: Python :: 3.11
Classifier: Programming Language :: Python :: 3.12
Classifier: Programming Language :: Python :: 3.13
Requires-Dist: docker (>=7.1.0,<8.0.0)
Requires-Dist: halo (>=0.0.31,<0.0.32)
Requires-Dist: pydantic (>=2.3.0,<3.0.0)
Requires-Dist: typer[all] (>=0.9.0,<0.10.0)
